{
  "title": "BMW 3 Series F34 N55 335i",
  "subtitle": "Мощный спортивный хэтчбек с турбированным 6-цилиндром",
  "description": "BMW 3 Series F34 N55 335i — это мощный спортивный хэтчбек с турбированным 6-цилиндровым двигателем N55 мощностью 306 л.с. Сочетает производительность с практичностью открывающегося багажника.",
  "advantages": [
    "Мощный турбированный двигатель N55",
    "Практичный формат хэтчбека",
    "Спортивный характер и динамика",
    "Хорошее оснащение и комфорт",
    "Отличная управляемость",
    "Надежная конструкция"
  ],
  "problems": [
    "Проблемы с турбокомпрессором при интенсивной езде",
    "Дорогое обслуживание и запасные части",
    "Сложная электроника требует диагностики",
    "Проблемы с масляным охладителем",
    "Высокий расход при спортивной езде",
    "Требует качественное синтетическое масло"
  ],
  "image": ""
}
